polars_indicator-0.1.1.dist-info/METADATA
polars_indicator-0.1.1.dist-info/WHEEL
polars_indicator-0.1.1.dist-info/licenses/LICENSE
polars_indicator/__init__.py
polars_indicator/_internal.abi3.so
polars_indicator/_internal.pyi
polars_indicator/typing.py
polars_indicator-0.1.1.dist-info/RECORD
