Metadata-Version: 2.4
Name: polars-indicator
Version: 0.1.1
Classifier: Development Status :: 3 - Alpha
Classifier: Intended Audience :: Developers
Classifier: Intended Audience :: Financial and Insurance Industry
Classifier: License :: OSI Approved :: MIT License
Classifier: Programming Language :: Rust
Classifier: Programming Language :: Python :: Implementation :: CPython
Classifier: Programming Language :: Python :: Implementation :: PyPy
Classifier: Programming Language :: Python :: 3
Classifier: Programming Language :: Python :: 3.8
Classifier: Programming Language :: Python :: 3.9
Classifier: Programming Language :: Python :: 3.10
Classifier: Programming Language :: Python :: 3.11
Classifier: Programming Language :: Python :: 3.12
Classifier: Topic :: Office/Business :: Financial
Classifier: Topic :: Scientific/Engineering
Requires-Dist: numpy>=1.24.4
Requires-Dist: polars>=1.8.2
Requires-Dist: polars-talib>=0.1.5
License-File: LICENSE
Summary: Technical indicators for Polars dataframes using Rust
Keywords: polars,technical-analysis,indicators,rust,finance
Author-email: Ender <codeotter0201@gmail.com>
Maintainer-email: Ender <codeotter0201@gmail.com>
License: MIT
Requires-Python: >=3.8
Project-URL: Homepage, https://github.com/codeotter0201/polars_indicator
Project-URL: Repository, https://github.com/codeotter0201/polars_indicator
Project-URL: Documentation, https://github.com/codeotter0201/polars_indicator#readme
Project-URL: Issues, https://github.com/codeotter0201/polars_indicator/issues
